anchorpy/__init__.py
anchorpy/borsh_extension.py
anchorpy/cli.py
anchorpy/error.py
anchorpy/idl.py
anchorpy/provider.py
anchorpy/py.typed
anchorpy/pytest_plugin.py
anchorpy/template.py
anchorpy/workspace.py
anchorpy/clientgen/__init__.py
anchorpy/clientgen/accounts.py
anchorpy/clientgen/common.py
anchorpy/clientgen/errors.py
anchorpy/clientgen/genpy_extension.py
anchorpy/clientgen/instructions.py
anchorpy/clientgen/program_id.py
anchorpy/clientgen/types.py
anchorpy/coder/__init__.py
anchorpy/coder/accounts.py
anchorpy/coder/coder.py
anchorpy/coder/common.py
anchorpy/coder/event.py
anchorpy/coder/idl.py
anchorpy/coder/instruction.py
anchorpy/program/__init__.py
anchorpy/program/common.py
anchorpy/program/context.py
anchorpy/program/core.py
anchorpy/program/event.py
anchorpy/program/namespace/__init__.py
anchorpy/program/namespace/account.py
anchorpy/program/namespace/instruction.py
anchorpy/program/namespace/methods.py
anchorpy/program/namespace/rpc.py
anchorpy/program/namespace/simulate.py
anchorpy/program/namespace/transaction.py
anchorpy/program/namespace/types.py
anchorpy/utils/__init__.py
anchorpy/utils/rpc.py
anchorpy/utils/token.py
anchorpy-0.20.2.dist-info/METADATA
anchorpy-0.20.2.dist-info/WHEEL
anchorpy-0.20.2.dist-info/entry_points.txt
anchorpy-0.20.2.dist-info/licenses/LICENSE
anchorpy-0.20.2.dist-info/RECORD
