Metadata-Version: 2.4
Name: anchorpy
Version: 0.20.2
Summary: The Python Anchor client.
Project-URL: Repository, https://github.com/kevinheavey/anchorpy
Project-URL: Documentation, https://kevinheavey.github.io/anchorpy/
Author-email: kevinheavey <kevinheavey123@gmail.com>
License-File: LICENSE
Requires-Python: ~=3.9
Requires-Dist: anchorpy-core<0.3,>=0.2.0
Requires-Dist: based58<0.2,>=0.1.1
Requires-Dist: borsh-construct<0.2,>=0.1.0
Requires-Dist: construct-typing<0.6,>=0.5.1
Requires-Dist: pyheck<0.2,>=0.1.4
Requires-Dist: solana<1.0,>=0.33.0
Requires-Dist: solders<1.0,>=0.21.0
Requires-Dist: toml<0.11,>=0.10.2
Requires-Dist: toolz<0.12,>=0.11.2
Provides-Extra: cli
Requires-Dist: autoflake~=1.4; extra == 'cli'
Requires-Dist: black<23,>=22.3.0; extra == 'cli'
Requires-Dist: genpy~=2021.1; extra == 'cli'
Requires-Dist: ipython<9,>=8.0.1; extra == 'cli'
Requires-Dist: typer==0.4.1; extra == 'cli'
Provides-Extra: pytest
Requires-Dist: py<2,>=1.11.0; extra == 'pytest'
Requires-Dist: pytest-asyncio<0.22,>=0.21.0; extra == 'pytest'
Requires-Dist: pytest-xprocess<0.19,>=0.18.1; extra == 'pytest'
Requires-Dist: pytest<8,>=7.2.0; extra == 'pytest'
